[
  {
    "id": "research_grants::humanities-undergraduate-mentoring-hum-grants",
    "source": "research_grants",
    "type": "opportunity",
    "name": "Humanities Undergraduate Mentoring (HUM) Grants",
    "url": "https://humgrants.byu.edu/",
    "text": "Humanities Undergraduate Mentoring (HUM) Grants -- BYU undergraduate research / mentored experiential learning grant funding.\nRelevant to: College of Humanities students (English, languages, linguistics, philosophy, comparative literature).\nThis is funding students can apply for to do research or creative work with a faculty mentor (great for grad school and resumes).\nHumanities majors\ncan apply for BYU\nHumanities Undergraduate Mentoring Grants\n(HUM Grants) through this site until November 1\n, 2026 at 10:00 p.m.\nRead this page carefully and apply below.\nInformation Sessions will be held October 6th and 7th at 2:00pm in 4010 JFSB.\nAs part of the college support for experiential learning, HUM grants offer resources for student-initiated, faculty-mentored research projects outside the classroom. Students can apply to the College of Humanities, with a faculty mentor’s endorsement, for up to $1,500 in scholarship funding to support their work.\nHUM Grant funded experiences should be high impact learning opportunities in which student and faculty research interests converge. A significant project with substantive mentoring should lead to improvement in core humanities learning outcomes, such as advanced research, writing, and presenting.\nEligibility:\nStudents\nmust be majoring in the College of Humanities\nand not have received a HUM Grant in the previous cycle (the last six months).\nProposed projects must be completable before graduation.\n(e.g., If you are graduating in April, you should apply in the previous fall cycle at the latest rather than winter.)\nMentors\nmust be full-time faculty in the College of Humanities\n. Faculty may only mentor up to two projects per cycle.\nStudents interested in proposing a project should consider the following HUM Grant criteria.\nStudent-initiated\nThe research should involve a subject of strong personal and intellectual interest. Students with some experience with the subject or research question, in the classroom or other contexts, will provide more compelling narratives of interest in their proposals.\nFaculty-mentored\nSuccessful projects will depend on a strong student/faculty mentoring relationship. Students should select faculty mentors carefully, based on their prior relationship and relevant field.\nFaculty mentors must be committed to meeting with their students regularly\n. Students must be majors in the college and mentors must be full-time faculty in the college.\nEnabling\nThe funding request, which will include a project budget, should show how the HUM grant will enable an opportunity (travel to an archive or an academic conference, technology or equipment purchase or rental, time spent, etc.) the student might not otherwise have. Funded projects should stand alone with distinct purpose and outcomes;\nfunding should not simply supplement participation in an existing program such as study abroad\n.\nAccountable\nThe proposed research should have specific outcomes that can be achieved within a manageable timetable. Students and mentors will report on the results at the conclusion of the grant period.\nAll proposals include the following elements. Use the proposal site linked below to create your proposal. It includes detailed prompts for each component:\nA statement of purpose and significance\nA detailed description of the research, its scope, and parameters\nA statement of expected academic outcomes—the anticipated product of research\nA description of the student and faculty mentor’s qualifications for the project\nA project timetable and budget\nA list of scholarly sources relevant to the research\nInformation Sessions\nOctober 6th and 7th at 2:00pm in 4010 JFSB\nHUM Grants Deadlines\nFall Cycle 202\n5\nWinter Cycle 202\n6\nProposal Due\nNovember 1, 2026\nMarch 7, 2026\nMentor Endorsement Due\nNovember 8, 2026\nMarch 14, 2026\nAwards Announced\nWeek of December 1, 2026\nWeek of April 1, 2026\nProject Outcomes Report Due\nAugust 7, 2027\nDecember 5, 2026\nMentor Outcomes Endorsement Due\nAugust 14, 2027\nDecember 12, 2026\nNOTE: Special funding available from the University Accessibility Center for students with disabilities. See proposal form for details.\nWith questions please contact:\ngrant_lundberg@byu.edu"
  },
  {
    "id": "research_grants::economics-experiential-learning-grant",
    "source": "research_grants",
    "type": "opportunity",
    "name": "Economics Experiential Learning Grant",
    "url": "https://economics.byu.edu/experiential-learning-grant",
    "text": "Economics Experiential Learning Grant -- BYU undergraduate research / mentored experiential learning grant funding.\nRelevant to: Economics students (FHSS).\nThis is funding students can apply for to do research or creative work with a faculty mentor (great for grad school and resumes).\nIn an effort to encourage more students to participate in experiential learning activities, BYU University Administration has provided funds to the Economics Department to assist students who would not be able to participate in these experiences without funding. This grant is to be used for field studies, studies abroad, mentored research, internships, conference presentations, etc.\nEligibility\n(applicants must meet each of the below criteria to be considered for a grant)\n1. You are a declared economics major.\nYou have successfully completed at least one on-campus economics course at BYU-Provo.\nYou have secured (or are currently applying for) an experience that will support your academic and career goals.\nYou have not already received an Internship or Experiential Learning Grant from the Economics Department for the same semester or term.\nNote: Students who qualify for a grant are eligible for only\none grant per semester or term\n.\nApplication Instructions\nThe Experiential Learning Grant is awarded on a rolling basis, without a set deadline. However, applications will ideally be received before the start of the experience for which you are applying. Applications will not be considered for any experience in the past. Apply as early in your Experiential Learning process as possible to secure funding.\nCompleted applications, including the required attachments indicated on the first page of the application, should be submitted via email to economics@byu.edu or hand-delivered to the Economics Department office in WVB 2146."
  },
  {
    "id": "research_grants::college-of-fine-arts-communications-student-scholarships-and-grants",
    "source": "research_grants",
    "type": "opportunity",
    "name": "College of Fine Arts & Communications Student Scholarships and Grants",
    "url": "https://cfac.byu.edu/student-scholarships-and-grants/",
    "text": "College of Fine Arts & Communications Student Scholarships and Grants -- BYU undergraduate research / mentored experiential learning grant funding.\nRelevant to: Fine Arts and Communications students (art, design, music, theatre, media arts, communications).\nThis is funding students can apply for to do research or creative work with a faculty mentor (great for grad school and resumes).\nResources\nScholarships & Grants\nDepartments and Programs\nStay Connected\nIMPORTANT STUDENT FUNDING OPPORTUNITIES\nDEPARTMENT AND SCHOOL FUNDING\nDepartment of Art\nSchool of Communications\nDepartment of Dance\nDepartment of Design\nSchool of Music\nDepartment of Theatre and Media Arts\nCOLLEGE FUNDING\nNAME\nDEADLINES\nLINK\nADDITIONAL INFO\nLaycock Center for Creative Collaboration\nSeptember 24, 2026; February 12, 2026\nClick here\nApplications submitted online\nApplication deadlines two times per year (February and September)\nProposals must be discussed with chair/director AT LEAST one week prior to the deadline\nReports submitted online\nhere\nUNIVERSITY FUNDING\nNAME\nDEADLINES\nLINK\nADDITIONAL INFO\nBYU Undergraduate Scholarships & Financial Aid\nVarious\nClick here\nGeorge H. Brimhall Memorial Essay Contest\nTBA (Previously September 28, 2023)\nClick here\nEssays submitted online to BYU Student Alumni\nApplications are due by 2 p.m. on the deadline date\nProfessional Presentation Award\nFebruary 11 (for Jan-June conferences); November 1 (for July-Dec conferences)\nClick here\nApplications submitted online to Graduate Student Society\nApplications are due by 5 p.m. on the deadline date.\nPhi Kappa Phi\nVarious\nClick here\nApplications submitted online to Phi Kappa Phi\nContact Daniel Everett for more information at\ndaniel_everett@byu.edu\nor 801-422-8006\nCharles Redd Center Grant Programs\nAnnually on March 15\nClick here\nApplications submitted to Charles Redd Center\nReligious Education Student Dissertation Grant\nAnnually by April 1\nClick here\nApplications submitted to Religious Education\nVera Hinckley Mayhew Student Creative Arts Contests\nVarious\nClick here\nApplications submitted to Mayhew Contests\nOFF-CAMPUS FUNDING\nNAME\nDEADLINES\nLINK\nADDITIONAL INFO\nUtah Conference on Undergraduate Research\nProposals due by November 8, 2024\nClick here\nWashington Award\nOn hiatus"
  }
]